{
  "name": "lavender-fields",
  "dark": false,
  "colors": {
    "bg_base": "#F3E8FF",
    "bg_elevated": "#EADCFD",
    "bg_overlay": "#E1D0FB",
    "bg_control": "#D8C4F9",
    "bg_control_hov": "#C4A8F5",
    "bg_control_prs": "#B98EF2",
    "accent": "#A78BFA",
    "accent_hover": "#C084FC",
    "accent_pressed": "#9333EA",
    "accent_subtle": "rgba(167, 139, 250, 0.1)",
    "border": "#EDE9FE59",
    "border_light": "#EDE9FE80",
    "border_focus": "#A78BFA",
    "text_primary": "#4C1D95",
    "text_secondary": "#6D28D9",
    "text_disabled": "#9CA3AF",
    "text_on_accent": "#FFFFFF",
    "success": "#22C55E",
    "danger": "#EF4444",
    "warning": "#F59E0B",
    "icon_folder": "#F59E0B",
    "icon_file": "#6D28D9",
    "sidebar_bg": "#F3E8FF",
    "sidebar_item": "#EADCFD",
    "sidebar_hover": "#E1D0FB",
    "sidebar_sel": "rgba(167, 139, 250, 0.1)",
    "sidebar_sel_bar": "#A78BFA"
  }
}